chift/.DS_Store
chift/README.md
chift/__init__.py
chift/api/__init__.py
chift/api/client.py
chift/api/exceptions.py
chift/api/mixins.py
chift/models/.DS_Store
chift/models/__init__.py
chift/models/consumers/__init__.py
chift/models/consumers/accounting/__init__.py
chift/models/consumers/banking/__init__.py
chift/models/consumers/commerce/__init__.py
chift/models/consumers/connection/__init__.py
chift/models/consumers/consumer.py
chift/models/consumers/custom/__init__.py
chift/models/consumers/data/__init__.py
chift/models/consumers/invoicing/__init__.py
chift/models/consumers/log/__init__.py
chift/models/consumers/payment/__init__.py
chift/models/consumers/pms/__init__.py
chift/models/consumers/pos/__init__.py
chift/models/consumers/sync/__init__.py
chift/models/datastores/__init__.py
chift/models/integrations/__init__.py
chift/models/syncs/__init__.py
chift/models/webhooks/__init__.py
chift/openapi/__init__.py
chift/openapi/chift_formatter.py
chift/openapi/models.py
chift/openapi/openapi.json
chift/openapi/openapi.py
chift-0.5.5.dist-info/METADATA
chift-0.5.5.dist-info/WHEEL
chift-0.5.5.dist-info/RECORD
