Metadata-Version: 2.4
Name: chift
Version: 0.5.5
Summary: Chift API client
Author: Henry Hertoghe
Author-email: henry.hertoghe@chift.eu
Requires-Python: >=3.9
Classifier: Programming Language :: Python :: 3
Classifier: Programming Language :: Python :: 3.9
Classifier: Programming Language :: Python :: 3.10
Classifier: Programming Language :: Python :: 3.11
Classifier: Programming Language :: Python :: 3.12
Classifier: Programming Language :: Python :: 3.13
Classifier: Programming Language :: Python :: 3.14
Requires-Dist: pydantic (>=2.7.2,<3.0.0)
Requires-Dist: requests (>=2.20)
